README.md
setup.cfg
setup.py
eventcore_sqs/__init__.py
eventcore_sqs/consumer.py
eventcore_sqs/producer.py
eventcore_sqs.egg-info/PKG-INFO
eventcore_sqs.egg-info/SOURCES.txt
eventcore_sqs.egg-info/dependency_links.txt
eventcore_sqs.egg-info/not-zip-safe
eventcore_sqs.egg-info/requires.txt
eventcore_sqs.egg-info/top_level.txt