Metadata-Version: 1.0
Name: eventcore-sqs
Version: 0.0.1
Summary: Produce and consume events with SQS.
Home-page: https://github.com/maikelboogerd/eventcore-sqs
Author: Maikel van den Boogerd
Author-email: maikelboogerd@gmail.com
License: MIT
Keywords: event,sqs,producer,consumer
Platform: UNKNOWN
